gittwig/__init__.py
gittwig/__main__.py
gittwig/app.py
gittwig/models/__init__.py
gittwig/models/git_models.py
gittwig/py.typed
gittwig/screens/__init__.py
gittwig/screens/confirm_delete.py
gittwig/screens/create_branch.py
gittwig/screens/help_screen.py
gittwig/services/__init__.py
gittwig/services/git_service.py
gittwig/styles.tcss
gittwig/widgets/__init__.py
gittwig/widgets/branch_list.py
gittwig/widgets/commit_list.py
gittwig/widgets/diff_viewer.py
gittwig/widgets/file_list.py
gittwig/widgets/pane_header.py
gittwig-0.2.4.dist-info/WHEEL
gittwig-0.2.4.dist-info/entry_points.txt
gittwig-0.2.4.dist-info/METADATA
gittwig-0.2.4.dist-info/RECORD
