Metadata-Version: 2.3
Name: gittwig
Version: 0.2.4
Summary: A terminal TUI application for managing Git branches
Author: Rhet Turnbull
Author-email: Rhet Turnbull <rturnbull@gmail.com>
Requires-Dist: textual>=0.80.0
Requires-Dist: bump2version ; extra == 'dev'
Requires-Dist: pytest>=8.0 ; extra == 'dev'
Requires-Dist: pytest-asyncio>=0.24 ; extra == 'dev'
Requires-Dist: ruff>=0.8 ; extra == 'dev'
Requires-Dist: mypy>=1.13 ; extra == 'dev'
Requires-Python: >=3.12
Provides-Extra: dev
